downloadmgr/__init__.py
downloadmgr/download.py
downloadmgr/init.py
downloadmgr-0.0.1.dist-info/METADATA
downloadmgr-0.0.1.dist-info/WHEEL
downloadmgr-0.0.1.dist-info/top_level.txt
downloadmgr-0.0.1.dist-info/RECORD
